[
  {
    "id": 1,
    "text": "The only limit to our realization of tomorrow is our doubts of today.",
    "authorName": "Franklin D. Roosevelt",
    "category": "motivation",
    "language": "en",
    "source": null,
    "likes": 0,
    "dateAdded": 1763548923642,
    "emoji": "ЁЯТк",
    "isFavorite": false
  },
  {
    "id": 4,
    "text": "In the middle of every difficulty lies opportunity.",
    "authorName": "Albert Einstein",
    "category": "motivation",
    "language": "en",
    "source": null,
    "likes": 0,
    "dateAdded": 1763548923642,
    "emoji": "тЬи",
    "isFavorite": false
  },
  {
    "id": 101,
    "text": "рдЬрд╣рд╛рдБ рдЪрд╛рд╣ рд╡рд╣рд╛рдБ рд░рд╛рд╣ред",
    "authorName": "Unknown",
    "category": "motivation",
    "language": "hi",
    "source": null,
    "likes": 0,
    "dateAdded": 1763548923642,
    "emoji": "ЁЯФе",
    "isFavorite": false
  },
  {
    "id": 105,
    "text": "рд╣рд╛рд░ рдордд рдорд╛рдиреЛ, рдЖрдЬ рдХреА рдореЗрд╣рдирдд рдХрд▓ рдХреА рдЬреАрдд рдмрдирддреА рд╣реИред",
    "authorName": "Unknown",
    "category": "motivation",
    "language": "hi",
    "source": null,
    "likes": 0,
    "dateAdded": 1763548923642,
    "emoji": "ЁЯПЖ",
    "isFavorite": false
  },
  {
    "id": 204,
    "text": "рк╣┘Е╪к рк░рк╛ркЦрлЛ, рк╕рклрк│ркдрк╛ ркЬрк▓рлНркжрлА ркЖрк╡рк╢рлЗ.",
    "authorName": "Unknown",
    "category": "motivation",
    "language": "gu",
    "source": null,
    "likes": 0,
    "dateAdded": 1763548923642,
    "emoji": "ЁЯТк",
    "isFavorite": false
  }
]